langgraph/__init__.py
langgraph/checkpoint/__init__.py
langgraph/checkpoint/django/__init__.py
langgraph/checkpoint/django/aio.py
langgraph/checkpoint/django/saver.py
langgraph/checkpoint/django/checkpoint/__init__.py
langgraph/checkpoint/django/checkpoint/apps.py
langgraph/checkpoint/django/checkpoint/models.py
langgraph/checkpoint/django/checkpoint/migrations/0001_initial.py
langgraph/checkpoint/django/checkpoint/migrations/__init__.py
langgraph_checkpoint_django-0.1.1.dist-info/licenses/LICENSE
langgraph_checkpoint_django-0.1.1.dist-info/METADATA
langgraph_checkpoint_django-0.1.1.dist-info/WHEEL
langgraph_checkpoint_django-0.1.1.dist-info/top_level.txt
langgraph_checkpoint_django-0.1.1.dist-info/RECORD
