Metadata-Version: 2.4
Name: langgraph-checkpoint-django
Version: 0.1.1
Summary: LangGraph checkpoint implementation for Django
Author-email: joongoo yun <devnine99@gmail.com>
Maintainer-email: joongoo yun <devnine99@gmail.com>
License: MIT
Project-URL: Homepage, https://github.com/devnine99/langgraph-checkpoint-django
Project-URL: Repository, https://github.com/devnine99/langgraph-checkpoint-django
Project-URL: Documentation, https://github.com/devnine99/langgraph-checkpoint-django#readme
Project-URL: Bug Tracker, https://github.com/devnine99/langgraph-checkpoint-django/issues
Project-URL: Changelog, https://github.com/devnine99/langgraph-checkpoint-django/blob/main/CHANGELOG.md
Keywords: langgraph,django,checkpoint,ai,graph
Classifier: Development Status :: 4 - Beta
Classifier: Intended Audience :: Developers
Classifier: License :: OSI Approved :: MIT License
Classifier: Operating System :: OS Independent
Classifier: Programming Language :: Python :: 3
Classifier: Programming Language :: Python :: 3.8
Classifier: Programming Language :: Python :: 3.9
Classifier: Programming Language :: Python :: 3.10
Classifier: Programming Language :: Python :: 3.11
Classifier: Programming Language :: Python :: 3.12
Classifier: Framework :: Django
Classifier: Framework :: Django :: 3.1
Classifier: Framework :: Django :: 3.2
Classifier: Framework :: Django :: 4.0
Classifier: Framework :: Django :: 4.1
Classifier: Framework :: Django :: 4.2
Classifier: Framework :: Django :: 5.0
Classifier: Topic :: Software Development :: Libraries :: Python Modules
Classifier: Topic :: Internet :: WWW/HTTP :: Dynamic Content
Requires-Python: >=3.8
License-File: LICENSE
Requires-Dist: django>=3.1
Requires-Dist: langgraph>=0.3.1
Provides-Extra: dev
Requires-Dist: pytest>=7.0; extra == "dev"
Requires-Dist: pytest-django>=4.5.0; extra == "dev"
Requires-Dist: black>=22.0; extra == "dev"
Requires-Dist: isort>=5.10; extra == "dev"
Requires-Dist: flake8>=4.0; extra == "dev"
Requires-Dist: mypy>=0.950; extra == "dev"
Requires-Dist: django-stubs>=1.12.0; extra == "dev"
Provides-Extra: test
Requires-Dist: pytest>=7.0; extra == "test"
Requires-Dist: pytest-django>=4.5.0; extra == "test"
Requires-Dist: pytest-cov>=3.0; extra == "test"
Dynamic: license-file
